statute_trees/__init__.py
statute_trees/nodes_codification.py
statute_trees/nodes_document.py
statute_trees/nodes_statute.py
statute_trees/resources.py
statute_trees/utils/__init__.py
statute_trees/utils/get.py
statute_trees/utils/layer.py
statute_trees/utils/set.py
statute_trees/utils/walk.py
statute_trees-0.1.5.dist-info/LICENSE
statute_trees-0.1.5.dist-info/METADATA
statute_trees-0.1.5.dist-info/WHEEL
statute_trees-0.1.5.dist-info/RECORD
