Metadata-Version: 2.1
Name: statute-trees
Version: 0.1.5
Summary: Tree-based Philippine Codifications, Statutes, and Documents, using a uniform node structure (i.e., leaves of a tree) identified by a given material path.
Home-page: https://lawsql.com
Author: Marcelino G. Veloso III
Author-email: mars@veloso.one
Requires-Python: >=3.11,<4.0
Classifier: Development Status :: 4 - Beta
Classifier: Framework :: Pydantic
Classifier: Framework :: Pytest
Classifier: Intended Audience :: Legal Industry
Classifier: Programming Language :: Python :: 3
Classifier: Programming Language :: Python :: 3.11
Classifier: Programming Language :: Python :: 3.11
Classifier: Typing :: Typed
Requires-Dist: citation-utils (>=0.2.11,<0.3.0)
Requires-Dist: statute-patterns (>=0.2.5,<0.3.0)
Project-URL: Documentation, https://github.com/justmars/statute-trees
Project-URL: Repository, https://github.com/justmars/statute-trees
